odoo/addons/project_task_subtask_parent_filter/README.rst
odoo/addons/project_task_subtask_parent_filter/__init__.py
odoo/addons/project_task_subtask_parent_filter/__manifest__.py
odoo/addons/project_task_subtask_parent_filter/readme/CONFIGURE.rst
odoo/addons/project_task_subtask_parent_filter/readme/CONTRIBUTORS.rst
odoo/addons/project_task_subtask_parent_filter/readme/DESCRIPTION.rst
odoo/addons/project_task_subtask_parent_filter/readme/USAGE.rst
odoo/addons/project_task_subtask_parent_filter/static/description/icon.png
odoo/addons/project_task_subtask_parent_filter/static/description/index.html
odoo/addons/project_task_subtask_parent_filter/views/project_task_views.xml
odoo_addon_project_task_subtask_parent_filter-16.0.1.0.0.1.dist-info/METADATA
odoo_addon_project_task_subtask_parent_filter-16.0.1.0.0.1.dist-info/WHEEL
odoo_addon_project_task_subtask_parent_filter-16.0.1.0.0.1.dist-info/top_level.txt
odoo_addon_project_task_subtask_parent_filter-16.0.1.0.0.1.dist-info/RECORD
